i_know_python/__init__.py
i_know_python/__version__.py
i_know_python/main.py
i_know_python/data/library37.txt
i_know_python-0.0.6.dist-info/LICENSE
i_know_python-0.0.6.dist-info/METADATA
i_know_python-0.0.6.dist-info/WHEEL
i_know_python-0.0.6.dist-info/entry_points.txt
i_know_python-0.0.6.dist-info/top_level.txt
i_know_python-0.0.6.dist-info/RECORD
