Metadata-Version: 2.1
Name: i-know-python
Version: 0.0.6
Summary: Find out how many of Python's standard library module's you've used.
Home-page: https://github.com/Jessime/i_know_python
Author: Jessime Kirk
Author-email: jessime.kirk@gmail.com
License: MIT
Platform: UNKNOWN
Classifier: License :: OSI Approved :: MIT License
Classifier: Natural Language :: English
Classifier: Programming Language :: Python :: 3.6
